<?xml version="1.0"?>
<controllers>
  <controller id="456" sector="S2" order="1">
    <mod>session</mod>
    <con>index</con>
    <sec>index</sec>
    <config>
      <displayTitle>true</displayTitle>
      <customTitle/>
    </config>
  </controller>
  <controller id="974" sector="S2" order="2">
    <mod>article</mod>
    <con>headlines</con>
    <sec>index</sec>
    <config>
      <displayTitle>true</displayTitle>
      <customTitle/>
      <headline_limit>3</headline_limit>
      <display_cat>all</display_cat>
    </config>
  </controller>
  <controller id="110" sector="S2" order="3">
    <mod>poll</mod>
    <con>view</con>
    <sec>index</sec>
    <config>
      <displayTitle>true</displayTitle>
      <customTitle/>
    </config>
  </controller>
  <controller id="119" sector="S1" order="1">
    <mod>menu</mod>
    <con>index</con>
    <sec>index</sec>
    <config>
      <displayTitle>false</displayTitle>
      <customTitle/>
      <display_category>3</display_category>
    </config>
  </controller>
</controllers>
